tradetransformrepo/TradeTransform.py
tradetransformrepo/__init__.py
tradetransformrepo/repository/TradeTransformRepository.py
tradetransformrepo/repository/__init__.py
tradetransformrepo/repository/serialize/__init__.py
tradetransformrepo/repository/serialize/trade_transform_deserializer.py
tradetransformrepo/repository/serialize/trade_transform_serializer.py
persuader_technology_automata_trade_transform_repository-0.1.2.dist-info/LICENSE
persuader_technology_automata_trade_transform_repository-0.1.2.dist-info/METADATA
persuader_technology_automata_trade_transform_repository-0.1.2.dist-info/WHEEL
persuader_technology_automata_trade_transform_repository-0.1.2.dist-info/top_level.txt
persuader_technology_automata_trade_transform_repository-0.1.2.dist-info/RECORD
